promptiva/__init__.py
promptiva/cli.py
promptiva-0.1.1.dist-info/LICENSE
promptiva-0.1.1.dist-info/METADATA
promptiva-0.1.1.dist-info/WHEEL
promptiva-0.1.1.dist-info/entry_points.txt
promptiva-0.1.1.dist-info/top_level.txt
promptiva-0.1.1.dist-info/RECORD
